mainprocess/README.MD
mainprocess/__init__.py
mainprocess/requirements.txt
mainprocess/thirdparty.json
mainprocess-0.11.dist-info/LICENSE.rst
mainprocess-0.11.dist-info/METADATA
mainprocess-0.11.dist-info/WHEEL
mainprocess-0.11.dist-info/top_level.txt
mainprocess-0.11.dist-info/RECORD
